monitaur/__init__.py
tests/unit/__init__.py
tests/unit/conftest.py
tests/unit/test_client.py
tests/unit/test_utils.py
monitaur-0.27.0.dist-info/METADATA
monitaur-0.27.0.dist-info/WHEEL
monitaur-0.27.0.dist-info/top_level.txt
monitaur-0.27.0.dist-info/RECORD
