Metadata-Version: 2.1
Name: monitaur
Version: 0.27.0
Summary: Monitaur Client Library
Home-page: UNKNOWN
Author: Michael Herman
Author-email: michael@monitaur.ai
License: MIT
Platform: UNKNOWN
Classifier: Development Status :: 2 - Pre-Alpha
Classifier: Intended Audience :: Developers
Classifier: Natural Language :: English
Classifier: Programming Language :: Python :: 3
Classifier: Programming Language :: Python :: 3.6
Classifier: Programming Language :: Python :: 3.7
Requires-Python: >=3.6, <3.9
Requires-Dist: boto3 (>=1.10.45)
Requires-Dist: dill (>=0.3.1.1)
Requires-Dist: requests (>=2.22.0)
Requires-Dist: numpy (>=1.18.1)
Requires-Dist: joblib (>=0.14.1)
Requires-Dist: mdutils (>=1.2.2)
Requires-Dist: mlflow (>=1.10.0)
